{
	"instance" : {
		"classForEffect" : "MarcusDenker 6/23/2015 17:31",
		"emitToByDo:" : "MarcusDenker 9/20/2013 15:04",
		"visitFullBlockNode:" : "ClementBera 6/27/2016 21:26",
		"visitNode:" : "JorgeRessia 5/6/2010 10:00",
		"ir" : "ajh 3/10/2003 17:59",
		"visitVariableNode:" : "MarcusDenker 5/22/2013 16:50",
		"translateFullBlock:" : "ClementBera 7/5/2016 10:24",
		"visitMethodNode:" : "cb 6/27/2013 16:53",
		"emitCondition:boolean:" : "ClementBera 6/26/2014 17:46",
		"emitIfFalseIfTrue:" : "ClementBera 7/10/2013 14:33",
		"emitToDo:step:" : "NicolaiHess 11/22/2015 20:07",
		"emitAnd:" : "ClementBera 7/10/2014 16:26",
		"visitAssignmentNode:" : "MarcusDenker 6/11/2013 15:52",
		"visitParseErrorNode:" : "MarcusDenker 5/9/2015 12:33",
		"emitToDo:" : "ClementBera 7/10/2013 14:08",
		"emitIfNotNilIfNil:" : "ClementBera 6/26/2014 17:41",
		"initialize" : "MarcusDenker 6/23/2015 17:32",
		"compilationContext" : "MarcusDenker 5/18/2013 17:38",
		"emitCaseOf:" : "ClementBera 5/26/2015 15:14",
		"emitCaseOf:otherwiseBlock:" : "ClementBera 5/26/2015 15:14",
		"visitLiteralNode:" : "MarcusDenker 4/11/2013 15:12",
		"visitSequenceNode:" : "nice 5/2/2013 00:22",
		"emitIfNilIfNotNil:" : "ClementBera 6/26/2014 17:41",
		"visitPragmaNode:" : "GuillermoPolito 6/6/2016 16:28",
		"emitRepeat:" : "KevinLanvin 7/17/2015 14:30",
		"emitIfNotNil:" : "nice 5/1/2013 21:01",
		"visitBlockNode:" : "ClementBera 6/29/2016 12:46",
		"emitIfTrueIfFalse:" : "ClementBera 7/10/2013 14:33",
		"emitCaseOfOtherwise:" : "ClementBera 5/26/2015 15:14",
		"emitOr:" : "ClementBera 7/10/2014 16:26",
		"visitLiteralArrayNode:" : "MarcusDenker 4/11/2013 15:12",
		"emitIfNil:" : "MarcusDenker 4/11/2013 15:12",
		"visitReturnNode:" : "MarcusDenker 4/11/2013 15:12",
		"visitCascadeNode:" : "nice 5/1/2013 16:13",
		"isEffectTranslator" : "pmm 7/19/2006 11:54",
		"isValueTranslator" : "pmm 7/19/2006 11:52",
		"visitArrayNode:" : "MarcusDenker 7/10/2013 16:20",
		"shouldBeSentToValueOrEffectTranslator" : "nice 5/1/2013 18:03",
		"emitIfTrue:" : "ClementBera 7/10/2013 14:13",
		"visitInlinedBlockNode:" : "MarcusDenker 4/11/2013 15:12",
		"visitLargeArrayNode:" : "ClementBera 7/19/2013 14:24",
		"visitMessageNode:" : "ClementBera 11/20/2013 19:36",
		"emitWhileFalse:" : "ClementBera 7/10/2013 14:11",
		"backendError:forNode:" : "MarcusDenker 9/23/2016 13:22",
		"emitMessageNode:" : "MarcusDenker 5/18/2013 17:41",
		"emitWhileTrue:" : "ClementBera 7/10/2013 14:11",
		"emitIfNil:boolean:" : "ClementBera 6/26/2014 17:45",
		"emitIf:boolean:" : "ClementBera 6/26/2014 17:42",
		"emitAllButLastCases:" : "ClementBera 7/10/2013 15:04",
		"emitWhile:boolean:" : "ClementBera 7/10/2013 14:10",
		"classForValue" : "MarcusDenker 6/23/2015 17:32",
		"emitIfFalse:" : "ClementBera 7/10/2013 14:13",
		"emitTimesRepeat:" : "ClementBera 7/26/2013 14:05"
	},
	"class" : {
		"initialize" : "KevinLanvin 7/17/2015 14:28"
	}
}