{
	"commentStamp" : "TorstenBergmann 2/4/2014 22:11",
	"super" : "Object",
	"category" : "FreeType-Settings",
	"classinstvars" : [
		"current"
	],
	"pools" : [
		"FT2Constants",
		"FreeTypeCacheConstants"
	],
	"classvars" : [
		"UpdateFontsAtImageStartup"
	],
	"instvars" : [
		"gamma",
		"hinting",
		"lightHinting",
		"subPixelAntiAliasing",
		"forceAutoHinting",
		"lcdHinting",
		"lcdvHinting",
		"monoHinting",
		"bitBltSubPixelAvailable",
		"subPixelFilters",
		"forceNonSubPixelCount",
		"gammaTable",
		"gammaInverseTable"
	],
	"name" : "FreeTypeSettings",
	"type" : "normal"
}