{
	"instance" : {
		"sizePushLiteral:" : " 7/19/2017 14:45:27",
		"rootNode:" : " 7/19/2017 14:45:27",
		"sizePushReceiver" : " 7/19/2017 14:45:27",
		"sizePushInstVar:" : " 7/19/2017 14:45:27",
		"methodStreamPosition" : " 7/19/2017 14:45:27",
		"sizePushNewArray:" : " 7/19/2017 14:45:27",
		"sizeStoreLiteralVar:" : " 7/19/2017 14:45:27",
		"sizePushSpecialLiteral:" : " 7/19/2017 14:45:27",
		"sizeOpcodeSelector:withArguments:" : " 7/19/2017 14:45:27",
		"sizeCallPrimitive:" : " 7/19/2017 14:45:27",
		"genPushNClosureTemps:" : " 7/19/2017 14:45:27",
		"sizeJumpLong:" : " 7/19/2017 14:45:27",
		"sizeReturnTopToCaller" : " 7/19/2017 14:45:27",
		"sizeStoreTemp:" : " 7/19/2017 14:45:27",
		"sizeBranchPopFalse:" : " 7/19/2017 14:45:27",
		"sizePushRemoteTemp:inVectorAt:" : " 7/19/2017 14:45:27",
		"supportsClosureOpcodes" : " 7/19/2017 14:45:27",
		"sizePushThisContext" : " 7/19/2017 14:45:27",
		"sizeReturnTop" : " 7/19/2017 14:45:27",
		"sizeSendSuper:numArgs:" : " 7/19/2017 14:45:27",
		"stream:" : " 7/19/2017 14:45:27",
		"sizeJump:" : " 7/19/2017 14:45:27",
		"sizePushLiteralVar:" : " 7/19/2017 14:45:27",
		"hasGeneratedMethod" : " 7/19/2017 14:45:27",
		"sizePop" : " 7/19/2017 14:45:27",
		"sizeReturnSpecialLiteral:" : " 7/19/2017 14:45:27",
		"sizePushTemp:" : " 7/19/2017 14:45:27",
		"rootNode" : " 7/19/2017 14:45:27",
		"noteBlockExtent:hasLocals:" : " 7/19/2017 14:45:27",
		"blockExtentsToTempsMap" : " 7/19/2017 14:45:27",
		"nextPut:" : " 7/19/2017 14:45:27",
		"sizeStorePopInstVarLong:" : " 7/19/2017 14:45:27",
		"sizePushClosureCopyNumCopiedValues:numArgs:jumpSize:" : " 7/19/2017 14:45:27",
		"outOfRangeError:index:range:to:" : " 7/19/2017 14:45:27",
		"genPushSpecialLiteral:" : " 7/19/2017 14:45:27",
		"sizeSend:numArgs:" : " 7/19/2017 14:45:27",
		"sizeStoreInstVarLong:" : " 7/19/2017 14:45:27",
		"sizeStorePopInstVar:" : " 7/19/2017 14:45:27",
		"sizeStorePopLiteralVar:" : " 7/19/2017 14:45:27",
		"sizeReturnReceiver" : " 7/19/2017 14:45:27",
		"sizePushConsArray:" : " 7/19/2017 14:45:27",
		"sizePushInstVarLong:" : " 7/19/2017 14:45:27",
		"bindAndJuggle:" : " 7/19/2017 14:45:27",
		"sizeStorePopRemoteTemp:inVectorAt:" : " 7/19/2017 14:45:27",
		"sizeStorePopTemp:" : " 7/19/2017 14:45:27",
		"sizeTrapIfNotInstanceOf:" : " 7/19/2017 14:45:27",
		"sizeStoreInstVar:" : " 7/19/2017 14:45:27",
		"sizeBranchPopTrue:" : " 7/19/2017 14:45:27",
		"sizeStoreRemoteTemp:inVectorAt:" : " 7/19/2017 14:45:27",
		"streamToMethod:" : " 7/19/2017 14:45:27",
		"sizeDup" : " 7/19/2017 14:45:27"
	},
	"class" : {
		"stackDeltaForPrimitive:in:" : " 7/19/2017 14:45:27",
		"nonExtensionBytecodeAt:in:" : " 7/19/2017 14:45:27",
		"specialSelectors" : " 7/19/2017 14:45:27"
	}
}