{
	"commentStamp" : "StephaneDucasse 6/7/2011 15:48",
	"super" : "Object",
	"category" : "System-Support",
	"classinstvars" : [ ],
	"pools" : [ ],
	"classvars" : [
		"CompilerClass",
		"LastImagePath",
		"LastQuitLogPosition",
		"LogFileName",
		"LowSpaceProcess",
		"LowSpaceSemaphore",
		"MemoryHogs",
		"SourceFileVersionString",
		"SpecialSelectors",
		"Tools"
	],
	"instvars" : [
		"globals",
		"deferredStartupActions",
		"specialObjectsArray",
		"session",
		"vm"
	],
	"name" : "SmalltalkImage",
	"type" : "normal"
}